relic/chunky/v1/__init__.py
relic/chunky/v1/definitions.py
relic/chunky/v1/py.typed
relic/chunky/v1/serialization.py
relic_tool_chunky_v1-2.0.0.dist-info/LICENSE.txt
relic_tool_chunky_v1-2.0.0.dist-info/METADATA
relic_tool_chunky_v1-2.0.0.dist-info/WHEEL
relic_tool_chunky_v1-2.0.0.dist-info/entry_points.txt
relic_tool_chunky_v1-2.0.0.dist-info/top_level.txt
relic_tool_chunky_v1-2.0.0.dist-info/RECORD
