Metadata-Version: 2.1
Name: relic-tool-chunky-v1
Version: 2.0.0
Summary: A library to read v1.1 Chunky files
Home-page: https://github.com/MAK-Relic-Tool/Relic-Tool-Chunky-V1
Author: Marcus Kertesz
Project-URL: Bug Tracker, https://github.com/MAK-Relic-Tool/Issue-Tracker/issues
Classifier: Programming Language :: Python :: 3 :: Only
Classifier: Programming Language :: Python :: 3.9
Classifier: Programming Language :: Python :: 3.10
Classifier: License :: OSI Approved :: GNU General Public License v3 (GPLv3)
Requires-Python: >=3.9
License-File: LICENSE.txt
Requires-Dist: mak-serialization-tools
Requires-Dist: relic-tool-chunky-core (~=1.1.0)
